pacage/__init__.py
oj_bz.sh-0.1.0.dist-info/METADATA
oj_bz.sh-0.1.0.dist-info/WHEEL
oj_bz.sh-0.1.0.dist-info/top_level.txt
oj_bz.sh-0.1.0.dist-info/RECORD
