Metadata-Version: 2.1
Name: oj-bz.sh
Version: 0.1.0
Summary: binary pacages for lambda 
Home-page: https://github.com/eldiabloj/osher-aws-project-int.git
Author: oj-bz
Author-email: osherbg@gmail.com
Classifier: Programming Language :: Python :: 3
Classifier: License :: OSI Approved :: MIT License
Classifier: Operating System :: OS Independent
Requires-Python: >=3.6
